{
  "id": "4297031",
  "name": "coffee-keep-accounts",
  "font_family": "iconfont",
  "css_prefix_text": "icon-",
  "description": "",
  "glyphs": [
    {
      "icon_id": "1718323",
      "name": "更多",
      "font_class": "edit-info-more",
      "unicode": "e601",
      "unicode_decimal": 58881
    },
    {
      "icon_id": "1304889",
      "name": "添加",
      "font_class": "add1",
      "unicode": "e622",
      "unicode_decimal": 58914
    },
    {
      "icon_id": "6947189",
      "name": "close",
      "font_class": "close",
      "unicode": "e62e",
      "unicode_decimal": 58926
    },
    {
      "icon_id": "38515090",
      "name": "首页",
      "font_class": "shouye-copy",
      "unicode": "100ce",
      "unicode_decimal": 65742
    },
    {
      "icon_id": "19449137",
      "name": "删除",
      "font_class": "shanchu",
      "unicode": "e630",
      "unicode_decimal": 58928
    },
    {
      "icon_id": "19465478",
      "name": "首页",
      "font_class": "shouye",
      "unicode": "f12d",
      "unicode_decimal": 61741
    },
    {
      "icon_id": "23306837",
      "name": "more_horizontal",
      "font_class": "more_horizontal",
      "unicode": "e7b9",
      "unicode_decimal": 59321
    },
    {
      "icon_id": "1904067",
      "name": "头像 男孩",
      "font_class": "icon-avatar",
      "unicode": "e667",
      "unicode_decimal": 58983
    },
    {
      "icon_id": "3558143",
      "name": "工资卡认证",
      "font_class": "wages",
      "unicode": "e627",
      "unicode_decimal": 58919
    },
    {
      "icon_id": "3844200",
      "name": "兼职",
      "font_class": "jianzhi",
      "unicode": "e68c",
      "unicode_decimal": 59020
    },
    {
      "icon_id": "3885955",
      "name": "西餐",
      "font_class": "_xican",
      "unicode": "e824",
      "unicode_decimal": 59428
    },
    {
      "icon_id": "5065483",
      "name": "统计",
      "font_class": "shuangsechangyongtubiao-",
      "unicode": "e608",
      "unicode_decimal": 58888
    },
    {
      "icon_id": "5218769",
      "name": "充值",
      "font_class": "chongzhi",
      "unicode": "e600",
      "unicode_decimal": 58880
    },
    {
      "icon_id": "6129075",
      "name": "40向下、展开",
      "font_class": "xiangxiazhankai",
      "unicode": "e767",
      "unicode_decimal": 59239
    },
    {
      "icon_id": "7417926",
      "name": "管理",
      "font_class": "guanli",
      "unicode": "e60d",
      "unicode_decimal": 58893
    },
    {
      "icon_id": "8452526",
      "name": "学习轨迹",
      "font_class": "xuexiguiji",
      "unicode": "e6c2",
      "unicode_decimal": 59074
    },
    {
      "icon_id": "12664884",
      "name": "交通",
      "font_class": "traffic",
      "unicode": "e60f",
      "unicode_decimal": 58895
    },
    {
      "icon_id": "12664899",
      "name": "娱乐",
      "font_class": "fun",
      "unicode": "e613",
      "unicode_decimal": 58899
    },
    {
      "icon_id": "12813773",
      "name": "back",
      "font_class": "back",
      "unicode": "e874",
      "unicode_decimal": 59508
    },
    {
      "icon_id": "17605430",
      "name": "通讯",
      "font_class": "tongxun",
      "unicode": "e80f",
      "unicode_decimal": 59407
    },
    {
      "icon_id": "17605485",
      "name": "设置",
      "font_class": "shezhi",
      "unicode": "e817",
      "unicode_decimal": 59415
    },
    {
      "icon_id": "17605489",
      "name": "购物",
      "font_class": "gouwu",
      "unicode": "e818",
      "unicode_decimal": 59416
    },
    {
      "icon_id": "18371113",
      "name": "添加",
      "font_class": "tianjia",
      "unicode": "e67a",
      "unicode_decimal": 59002
    },
    {
      "icon_id": "19449144",
      "name": "添加",
      "font_class": "tianjia1",
      "unicode": "e62f",
      "unicode_decimal": 58927
    },
    {
      "icon_id": "19449181",
      "name": "关于",
      "font_class": "guanyu",
      "unicode": "e634",
      "unicode_decimal": 58932
    },
    {
      "icon_id": "20336477",
      "name": "我的",
      "font_class": "wode",
      "unicode": "e609",
      "unicode_decimal": 58889
    },
    {
      "icon_id": "20919660",
      "name": "红包",
      "font_class": "hongbao",
      "unicode": "f422",
      "unicode_decimal": 62498
    },
    {
      "icon_id": "26154406",
      "name": "编辑",
      "font_class": "bianji",
      "unicode": "e70c",
      "unicode_decimal": 59148
    },
    {
      "icon_id": "29457069",
      "name": "医疗_现金支付",
      "font_class": "yiliao_xianjinzhifu",
      "unicode": "e641",
      "unicode_decimal": 58945
    },
    {
      "icon_id": "29797337",
      "name": "添加",
      "font_class": "tianjia2",
      "unicode": "100cd",
      "unicode_decimal": 65741
    },
    {
      "icon_id": "38515091",
      "name": "我的",
      "font_class": "wode-copy",
      "unicode": "100cf",
      "unicode_decimal": 65743
    },
    {
      "icon_id": "12296954",
      "name": "理财",
      "font_class": "licai1",
      "unicode": "e614",
      "unicode_decimal": 58900
    },
    {
      "icon_id": "12296972",
      "name": "转账",
      "font_class": "zhuanzhang1",
      "unicode": "e619",
      "unicode_decimal": 58905
    },
    {
      "icon_id": "5081416",
      "name": "咖啡",
      "font_class": "kafei",
      "unicode": "e6c6",
      "unicode_decimal": 59078
    }
  ]
}
